slowbreak/__init__.py
slowbreak/__version__.py
slowbreak/app.py
slowbreak/barebones_session.py
slowbreak/bursty_queue.py
slowbreak/comm.py
slowbreak/constants.py
slowbreak/message.py
slowbreak/mock_session.py
slowbreak/mock_socket.py
slowbreak/session.py
slowbreak/example/__init__.py
slowbreak/example/client1.py
slowbreak/example/client2.py
slowbreak/example/server1.py
slowbreak/util/__init__.py
slowbreak/util/create_server_key.py
slowbreak-0.0.16.dist-info/DESCRIPTION.rst
slowbreak-0.0.16.dist-info/METADATA
slowbreak-0.0.16.dist-info/RECORD
slowbreak-0.0.16.dist-info/WHEEL
slowbreak-0.0.16.dist-info/metadata.json
slowbreak-0.0.16.dist-info/top_level.txt
